Metadata-Version: 2.1
Name: KevinSR
Version: 0.1.20
Summary: This package includes inference codes supporting Super-resolution image and mask interpolations.
Home-page: https://pypi.org/project/KevinSR
Author: Kevin Zhang
Author-email: zhangkuanmayo@gmail.com
Classifier: Programming Language :: Python :: 3
Classifier: License :: OSI Approved :: MIT License
Classifier: Operating System :: OS Independent
Requires-Python: >=3.6.1
